HibernateKuangjiaRumenjiaochengCYuyanBianchengWang/README.md
HibernateKuangjiaRumenjiaochengCYuyanBianchengWang/__init__.py
HibernateKuangjiaRumenjiaochengCYuyanBianchengWang/__main__.py
HibernateKuangjiaRumenjiaochengCYuyanBianchengWang/file.epub
HibernateKuangjiaRumenjiaochengCYuyanBianchengWang/index.html
HibernateKuangjiaRumenjiaochengCYuyanBianchengWang/css/__init__.py
HibernateKuangjiaRumenjiaochengCYuyanBianchengWang/css/annotations.css
HibernateKuangjiaRumenjiaochengCYuyanBianchengWang/css/main.css
HibernateKuangjiaRumenjiaochengCYuyanBianchengWang/css/normalize.css
HibernateKuangjiaRumenjiaochengCYuyanBianchengWang/css/popup.css
HibernateKuangjiaRumenjiaochengCYuyanBianchengWang/font/__init__.py
HibernateKuangjiaRumenjiaochengCYuyanBianchengWang/font/fontello.eot
HibernateKuangjiaRumenjiaochengCYuyanBianchengWang/font/fontello.svg
HibernateKuangjiaRumenjiaochengCYuyanBianchengWang/font/fontello.ttf
HibernateKuangjiaRumenjiaochengCYuyanBianchengWang/font/fontello.woff
HibernateKuangjiaRumenjiaochengCYuyanBianchengWang/img/__init__.py
HibernateKuangjiaRumenjiaochengCYuyanBianchengWang/img/annotator-glyph-sprite.png
HibernateKuangjiaRumenjiaochengCYuyanBianchengWang/img/annotator-icon-sprite.png
HibernateKuangjiaRumenjiaochengCYuyanBianchengWang/img/apple-touch-icon.png
HibernateKuangjiaRumenjiaochengCYuyanBianchengWang/img/cancelfullscreen.png
HibernateKuangjiaRumenjiaochengCYuyanBianchengWang/img/close.png
HibernateKuangjiaRumenjiaochengCYuyanBianchengWang/img/fullscreen.png
HibernateKuangjiaRumenjiaochengCYuyanBianchengWang/img/loader.gif
HibernateKuangjiaRumenjiaochengCYuyanBianchengWang/img/menu-icon.png
HibernateKuangjiaRumenjiaochengCYuyanBianchengWang/img/save.png
HibernateKuangjiaRumenjiaochengCYuyanBianchengWang/img/saved.png
HibernateKuangjiaRumenjiaochengCYuyanBianchengWang/img/settings-s.png
HibernateKuangjiaRumenjiaochengCYuyanBianchengWang/img/settings.png
HibernateKuangjiaRumenjiaochengCYuyanBianchengWang/img/star.png
hibernate_kuangjia_rumenjiaocheng_c_yuyan_biancheng_wang-2024.3.5.0.dist-info/METADATA
hibernate_kuangjia_rumenjiaocheng_c_yuyan_biancheng_wang-2024.3.5.0.dist-info/WHEEL
hibernate_kuangjia_rumenjiaocheng_c_yuyan_biancheng_wang-2024.3.5.0.dist-info/entry_points.txt
hibernate_kuangjia_rumenjiaocheng_c_yuyan_biancheng_wang-2024.3.5.0.dist-info/top_level.txt
hibernate_kuangjia_rumenjiaocheng_c_yuyan_biancheng_wang-2024.3.5.0.dist-info/RECORD
